nltkma/__init__.py
nltkma/cli.py
nltkma/collections.py
nltkma/collocations.py
nltkma/compat.py
nltkma/data.py
nltkma/decorators.py
nltkma/downloader.py
nltkma/featstruct.py
nltkma/grammar.py
nltkma/help.py
nltkma/internals.py
nltkma/jsontags.py
nltkma/lazyimport.py
nltkma/probability.py
nltkma/text.py
nltkma/tgrep.py
nltkma/toolbox.py
nltkma/tree.py
nltkma/treeprettyprinter.py
nltkma/treetransforms.py
nltkma/util.py
nltkma/wsd.py
nltkma/chunk/__init__.py
nltkma/chunk/api.py
nltkma/chunk/named_entity.py
nltkma/chunk/regexp.py
nltkma/chunk/util.py
nltkma/classify/__init__.py
nltkma/classify/api.py
nltkma/classify/decisiontree.py
nltkma/classify/maxent.py
nltkma/classify/megam.py
nltkma/classify/naivebayes.py
nltkma/classify/positivenaivebayes.py
nltkma/classify/rte_classify.py
nltkma/classify/scikitlearn.py
nltkma/classify/senna.py
nltkma/classify/svm.py
nltkma/classify/tadm.py
nltkma/classify/textcat.py
nltkma/classify/util.py
nltkma/classify/weka.py
nltkma/cluster/__init__.py
nltkma/cluster/api.py
nltkma/cluster/em.py
nltkma/cluster/gaac.py
nltkma/cluster/kmeans.py
nltkma/cluster/util.py
nltkma/corpus/__init__.py
nltkma/corpus/europarl_raw.py
nltkma/corpus/util.py
nltkma/corpus/reader/__init__.py
nltkma/corpus/reader/aligned.py
nltkma/corpus/reader/api.py
nltkma/corpus/reader/bnc.py
nltkma/corpus/reader/bracket_parse.py
nltkma/corpus/reader/categorized_sents.py
nltkma/corpus/reader/chasen.py
nltkma/corpus/reader/childes.py
nltkma/corpus/reader/chunked.py
nltkma/corpus/reader/cmudict.py
nltkma/corpus/reader/comparative_sents.py
nltkma/corpus/reader/conll.py
nltkma/corpus/reader/crubadan.py
nltkma/corpus/reader/dependency.py
nltkma/corpus/reader/framenet.py
nltkma/corpus/reader/ieer.py
nltkma/corpus/reader/indian.py
nltkma/corpus/reader/ipipan.py
nltkma/corpus/reader/knbc.py
nltkma/corpus/reader/lin.py
nltkma/corpus/reader/mte.py
nltkma/corpus/reader/nkjp.py
nltkma/corpus/reader/nombank.py
nltkma/corpus/reader/nps_chat.py
nltkma/corpus/reader/opinion_lexicon.py
nltk_ma-0.0.6.dist-info/AUTHORS.md
nltk_ma-0.0.6.dist-info/LICENSE.txt
nltk_ma-0.0.6.dist-info/METADATA
nltk_ma-0.0.6.dist-info/README.md
nltk_ma-0.0.6.dist-info/WHEEL
nltk_ma-0.0.6.dist-info/entry_points.txt
nltk_ma-0.0.6.dist-info/top_level.txt
nltk_ma-0.0.6.dist-info/RECORD
